RapidViz/__init__.py
RapidViz/rapidviz.py
rapidviz-0.0.1.dist-info/LICENSE
rapidviz-0.0.1.dist-info/METADATA
rapidviz-0.0.1.dist-info/WHEEL
rapidviz-0.0.1.dist-info/top_level.txt
rapidviz-0.0.1.dist-info/RECORD
